dataslots/__init__.py
dataslots/py.typed
dataslots-1.2.0.dist-info/LICENSE
dataslots-1.2.0.dist-info/METADATA
dataslots-1.2.0.dist-info/WHEEL
dataslots-1.2.0.dist-info/top_level.txt
dataslots-1.2.0.dist-info/RECORD
