Metadata-Version: 2.1
Name: dataslots
Version: 1.2.0
Summary: Decorator to add __slots__ in dataclasses
Home-page: https://github.com/starhel/dataslots
Author: Adrian Stachlewski
Author-email: starhel.github@gmail.com
License: MIT
Project-URL: Source, https://github.com/starhel/dataslots
Project-URL: Tracker, https://github.com/starhel/dataslots/issues
Project-URL: Documentation, https://github.com/starhel/dataslots
Keywords: dataslots slots dataclasses
Classifier: Development Status :: 5 - Production/Stable
Classifier: License :: OSI Approved :: MIT License
Classifier: Programming Language :: Python :: 3.7
Classifier: Programming Language :: Python :: 3.8
Classifier: Programming Language :: Python :: 3.9
Classifier: Programming Language :: Python :: 3.10
Classifier: Programming Language :: Python :: 3.11
Classifier: Programming Language :: Python :: Implementation :: CPython
Classifier: Programming Language :: Python :: Implementation :: PyPy
Classifier: Intended Audience :: Developers
Classifier: Typing :: Typed
Requires-Python: >=3.7
License-File: LICENSE
Requires-Dist: typing-extensions (>=4.2.0) ; python_version < "3.11"
